{
  "updated_at": "2026-07-22T18:44:38.658258+00:00",
  "source": "live_last_updated_cache",
  "count": 2,
  "events": [
    {
      "event_id": 216512,
      "last_updated": "2026-07-22T18:44:10Z",
      "status": "inprogress",
      "current_minute": 82,
      "home_score": 1,
      "away_score": 0
    },
    {
      "event_id": 216511,
      "last_updated": "2026-07-22T18:44:09Z",
      "status": "inprogress",
      "current_minute": 56,
      "home_score": 1,
      "away_score": 0
    }
  ]
}