{
  "updated_at": "2026-06-03T09:36:02.396934+00:00",
  "source": "odds_snapshot_v1",
  "count": 149,
  "snapshot": {
    "10278|1x2|HOME": {
      "event_id": 10278,
      "market": "1x2",
      "outcome": "HOME",
      "decimal_odds": 1.42,
      "bookmaker": "consensus",
      "bookmakers_count": 15
    },
    "10278|1x2|DRAW": {
      "event_id": 10278,
      "market": "1x2",
      "outcome": "DRAW",
      "decimal_odds": 5.73,
      "bookmaker": "1xbet",
      "bookmakers_count": 15
    },
    "10278|1x2|AWAY": {
      "event_id": 10278,
      "market": "1x2",
      "outcome": "AWAY",
      "decimal_odds": 11.5,
      "bookmaker": "betsson",
      "bookmakers_count": 15
    },
    "10278|over_under_15|OVER": {
      "event_id": 10278,
      "market": "over_under_15",
      "outcome": "OVER",
      "decimal_odds": 1.27,
      "bookmaker": "betano",
      "bookmakers_count": 1
    },
    "10278|over_under_15|UNDER": {
      "event_id": 10278,
      "market": "over_under_15",
      "outcome": "UNDER",
      "decimal_odds": 3.77,
      "bookmaker": "pinnacle",
      "bookmakers_count": 1
    },
    "10278|over_under_25|OVER": {
      "event_id": 10278,
      "market": "over_under_25",
      "outcome": "OVER",
      "decimal_odds": 1.847,
      "bookmaker": "1xbet",
      "bookmakers_count": 1
    },
    "10278|over_under_25|UNDER": {
      "event_id": 10278,
      "market": "over_under_25",
      "outcome": "UNDER",
      "decimal_odds": 2.087,
      "bookmaker": "1xbet",
      "bookmakers_count": 1
    },
    "10278|over_under_35|OVER": {
      "event_id": 10278,
      "market": "over_under_35",
      "outcome": "OVER",
      "decimal_odds": 3.0,
      "bookmaker": "bet365",
      "bookmakers_count": 1
    },
    "10278|over_under_35|UNDER": {
      "event_id": 10278,
      "market": "over_under_35",
      "outcome": "UNDER",
      "decimal_odds": 1.39,
      "bookmaker": "betano",
      "bookmakers_count": 1
    },
    "10278|btts|YES": {
      "event_id": 10278,
      "market": "btts",
      "outcome": "YES",
      "decimal_odds": 2.42,
      "bookmaker": "pinnacle",
      "bookmakers_count": 15
    },
    "10278|btts|NO": {
      "event_id": 10278,
      "market": "btts",
      "outcome": "NO",
      "decimal_odds": 1.7,
      "bookmaker": "consensus",
      "bookmakers_count": 15
    },
    "206693|1x2|HOME": {
      "event_id": 206693,
      "market": "1x2",
      "outcome": "HOME",
      "decimal_odds": 3.34,
      "bookmaker": "1xbet",
      "bookmakers_count": 13
    },
    "206693|1x2|DRAW": {
      "event_id": 206693,
      "market": "1x2",
      "outcome": "DRAW",
      "decimal_odds": 3.575,
      "bookmaker": "1xbet",
      "bookmakers_count": 13
    },
    "206693|1x2|AWAY": {
      "event_id": 206693,
      "market": "1x2",
      "outcome": "AWAY",
      "decimal_odds": 2.28,
      "bookmaker": "consensus",
      "bookmakers_count": 13
    },
    "206693|over_under_15|OVER": {
      "event_id": 206693,
      "market": "over_under_15",
      "outcome": "OVER",
      "decimal_odds": 1.3,
      "bookmaker": "betano",
      "bookmakers_count": 1
    },
    "206693|over_under_15|UNDER": {
      "event_id": 206693,
      "market": "over_under_15",
      "outcome": "UNDER",
      "decimal_odds": 3.5,
      "bookmaker": "bet365",
      "bookmakers_count": 1
    },
    "206693|over_under_25|OVER": {
      "event_id": 206693,
      "market": "over_under_25",
      "outcome": "OVER",
      "decimal_odds": 1.965,
      "bookmaker": "1xbet",
      "bookmakers_count": 1
    },
    "206693|over_under_25|UNDER": {
      "event_id": 206693,
      "market": "over_under_25",
      "outcome": "UNDER",
      "decimal_odds": 1.955,
      "bookmaker": "1xbet",
      "bookmakers_count": 1
    },
    "206693|over_under_35|OVER": {
      "event_id": 206693,
      "market": "over_under_35",
      "outcome": "OVER",
      "decimal_odds": 3.27,
      "bookmaker": "consensus",
      "bookmakers_count": 1
    },
    "206693|over_under_35|UNDER": {
      "event_id": 206693,
      "market": "over_under_35",
      "outcome": "UNDER",
      "decimal_odds": 1.35,
      "bookmaker": "betano",
      "bookmakers_count": 1
    },
    "206693|btts|YES": {
      "event_id": 206693,
      "market": "btts",
      "outcome": "YES",
      "decimal_odds": 1.73,
      "bookmaker": "novibet",
      "bookmakers_count": 12
    },
    "206693|btts|NO": {
      "event_id": 206693,
      "market": "btts",
      "outcome": "NO",
      "decimal_odds": 2.07,
      "bookmaker": "betano",
      "bookmakers_count": 12
    },
    "9973|1x2|HOME": {
      "event_id": 9973,
      "market": "1x2",
      "outcome": "HOME",
      "decimal_odds": 2.03,
      "bookmaker": "pinnacle",
      "bookmakers_count": 14
    },
    "9973|1x2|DRAW": {
      "event_id": 9973,
      "market": "1x2",
      "outcome": "DRAW",
      "decimal_odds": 3.1,
      "bookmaker": "sportingbet",
      "bookmakers_count": 14
    },
    "9973|1x2|AWAY": {
      "event_id": 9973,
      "market": "1x2",
      "outcome": "AWAY",
      "decimal_odds": 4.28,
      "bookmaker": "pinnacle",
      "bookmakers_count": 14
    },
    "9973|over_under_15|OVER": {
      "event_id": 9973,
      "market": "over_under_15",
      "outcome": "OVER",
      "decimal_odds": 1.5,
      "bookmaker": "betano",
      "bookmakers_count": 1
    },
    "9973|over_under_15|UNDER": {
      "event_id": 9973,
      "market": "over_under_15",
      "outcome": "UNDER",
      "decimal_odds": 2.58,
      "bookmaker": "pinnacle",
      "bookmakers_count": 1
    },
    "9973|over_under_25|OVER": {
      "event_id": 9973,
      "market": "over_under_25",
      "outcome": "OVER",
      "decimal_odds": 2.59,
      "bookmaker": "pinnacle",
      "bookmakers_count": 1
    },
    "9973|over_under_25|UNDER": {
      "event_id": 9973,
      "market": "over_under_25",
      "outcome": "UNDER",
      "decimal_odds": 1.51,
      "bookmaker": "novibet",
      "bookmakers_count": 1
    },
    "9973|over_under_35|OVER": {
      "event_id": 9973,
      "market": "over_under_35",
      "outcome": "OVER",
      "decimal_odds": 5.0,
      "bookmaker": "bet365",
      "bookmakers_count": 1
    },
    "9973|over_under_35|UNDER": {
      "event_id": 9973,
      "market": "over_under_35",
      "outcome": "UNDER",
      "decimal_odds": 1.18,
      "bookmaker": "betano",
      "bookmakers_count": 1
    },
    "9973|btts|YES": {
      "event_id": 9973,
      "market": "btts",
      "outcome": "YES",
      "decimal_odds": 2.2,
      "bookmaker": "bet365",
      "bookmakers_count": 13
    },
    "9973|btts|NO": {
      "event_id": 9973,
      "market": "btts",
      "outcome": "NO",
      "decimal_odds": 1.67,
      "bookmaker": "betano",
      "bookmakers_count": 13
    },
    "209436|1x2|HOME": {
      "event_id": 209436,
      "market": "1x2",
      "outcome": "HOME",
      "decimal_odds": 3.92,
      "bookmaker": "consensus",
      "bookmakers_count": 3
    },
    "209436|1x2|DRAW": {
      "event_id": 209436,
      "market": "1x2",
      "outcome": "DRAW",
      "decimal_odds": 3.31,
      "bookmaker": "consensus",
      "bookmakers_count": 3
    },
    "209436|1x2|AWAY": {
      "event_id": 209436,
      "market": "1x2",
      "outcome": "AWAY",
      "decimal_odds": 1.81,
      "bookmaker": "consensus",
      "bookmakers_count": 3
    },
    "209436|over_under_15|OVER": {
      "event_id": 209436,
      "market": "over_under_15",
      "outcome": "OVER",
      "decimal_odds": 1.35,
      "bookmaker": "consensus",
      "bookmakers_count": 1
    },
    "209436|over_under_15|UNDER": {
      "event_id": 209436,
      "market": "over_under_15",
      "outcome": "UNDER",
      "decimal_odds": 2.83,
      "bookmaker": "consensus",
      "bookmakers_count": 1
    },
    "209436|over_under_25|OVER": {
      "event_id": 209436,
      "market": "over_under_25",
      "outcome": "OVER",
      "decimal_odds": 2.22,
      "bookmaker": "consensus",
      "bookmakers_count": 1
    },
    "209436|over_under_25|UNDER": {
      "event_id": 209436,
      "market": "over_under_25",
      "outcome": "UNDER",
      "decimal_odds": 1.56,
      "bookmaker": "consensus",
      "bookmakers_count": 1
    },
    "209436|btts|YES": {
      "event_id": 209436,
      "market": "btts",
      "outcome": "YES",
      "decimal_odds": 2.02,
      "bookmaker": "consensus",
      "bookmakers_count": 3
    },
    "209436|btts|NO": {
      "event_id": 209436,
      "market": "btts",
      "outcome": "NO",
      "decimal_odds": 1.67,
      "bookmaker": "consensus",
      "bookmakers_count": 3
    },
    "209443|1x2|HOME": {
      "event_id": 209443,
      "market": "1x2",
      "outcome": "HOME",
      "decimal_odds": 14.5,
      "bookmaker": "consensus",
      "bookmakers_count": 3
    },
    "209443|1x2|DRAW": {
      "event_id": 209443,
      "market": "1x2",
      "outcome": "DRAW",
      "decimal_odds": 6.86,
      "bookmaker": "consensus",
      "bookmakers_count": 3
    },
    "209443|1x2|AWAY": {
      "event_id": 209443,
      "market": "1x2",
      "outcome": "AWAY",
      "decimal_odds": 1.1,
      "bookmaker": "consensus",
      "bookmakers_count": 3
    },
    "209443|over_under_25|OVER": {
      "event_id": 209443,
      "market": "over_under_25",
      "outcome": "OVER",
      "decimal_odds": 1.42,
      "bookmaker": "consensus",
      "bookmakers_count": 1
    },
    "209443|over_under_25|UNDER": {
      "event_id": 209443,
      "market": "over_under_25",
      "outcome": "UNDER",
      "decimal_odds": 2.58,
      "bookmaker": "consensus",
      "bookmakers_count": 1
    },
    "209443|over_under_35|OVER": {
      "event_id": 209443,
      "market": "over_under_35",
      "outcome": "OVER",
      "decimal_odds": 2.16,
      "bookmaker": "consensus",
      "bookmakers_count": 1
    },
    "209443|over_under_35|UNDER": {
      "event_id": 209443,
      "market": "over_under_35",
      "outcome": "UNDER",
      "decimal_odds": 1.59,
      "bookmaker": "consensus",
      "bookmakers_count": 1
    },
    "209443|btts|YES": {
      "event_id": 209443,
      "market": "btts",
      "outcome": "YES",
      "decimal_odds": 2.07,
      "bookmaker": "consensus",
      "bookmakers_count": 3
    },
    "209443|btts|NO": {
      "event_id": 209443,
      "market": "btts",
      "outcome": "NO",
      "decimal_odds": 1.64,
      "bookmaker": "consensus",
      "bookmakers_count": 3
    },
    "206691|1x2|HOME": {
      "event_id": 206691,
      "market": "1x2",
      "outcome": "HOME",
      "decimal_odds": 1.18,
      "bookmaker": "consensus",
      "bookmakers_count": 13
    },
    "206691|1x2|DRAW": {
      "event_id": 206691,
      "market": "1x2",
      "outcome": "DRAW",
      "decimal_odds": 9.45,
      "bookmaker": "1xbet",
      "bookmakers_count": 13
    },
    "206691|1x2|AWAY": {
      "event_id": 206691,
      "market": "1x2",
      "outcome": "AWAY",
      "decimal_odds": 28.0,
      "bookmaker": "1xbet",
      "bookmakers_count": 13
    },
    "206691|over_under_15|OVER": {
      "event_id": 206691,
      "market": "over_under_15",
      "outcome": "OVER",
      "decimal_odds": 1.13,
      "bookmaker": "betano",
      "bookmakers_count": 1
    },
    "206691|over_under_15|UNDER": {
      "event_id": 206691,
      "market": "over_under_15",
      "outcome": "UNDER",
      "decimal_odds": 6.0,
      "bookmaker": "bet365",
      "bookmakers_count": 1
    },
    "206691|over_under_25|OVER": {
      "event_id": 206691,
      "market": "over_under_25",
      "outcome": "OVER",
      "decimal_odds": 1.42,
      "bookmaker": "consensus",
      "bookmakers_count": 1
    },
    "206691|over_under_25|UNDER": {
      "event_id": 206691,
      "market": "over_under_25",
      "outcome": "UNDER",
      "decimal_odds": 2.95,
      "bookmaker": "betsson",
      "bookmakers_count": 1
    },
    "206691|over_under_35|OVER": {
      "event_id": 206691,
      "market": "over_under_35",
      "outcome": "OVER",
      "decimal_odds": 2.1,
      "bookmaker": "888sport",
      "bookmakers_count": 1
    },
    "206691|over_under_35|UNDER": {
      "event_id": 206691,
      "market": "over_under_35",
      "outcome": "UNDER",
      "decimal_odds": 1.935,
      "bookmaker": "1xbet",
      "bookmakers_count": 1
    },
    "206691|btts|YES": {
      "event_id": 206691,
      "market": "btts",
      "outcome": "YES",
      "decimal_odds": 2.28,
      "bookmaker": "1xbet",
      "bookmakers_count": 13
    },
    "206691|btts|NO": {
      "event_id": 206691,
      "market": "btts",
      "outcome": "NO",
      "decimal_odds": 1.7,
      "bookmaker": "betsson",
      "bookmakers_count": 13
    },
    "207466|1x2|HOME": {
      "event_id": 207466,
      "market": "1x2",
      "outcome": "HOME",
      "decimal_odds": 1.848,
      "bookmaker": "1xbet",
      "bookmakers_count": 7
    },
    "207466|1x2|DRAW": {
      "event_id": 207466,
      "market": "1x2",
      "outcome": "DRAW",
      "decimal_odds": 3.715,
      "bookmaker": "1xbet",
      "bookmakers_count": 7
    },
    "207466|1x2|AWAY": {
      "event_id": 207466,
      "market": "1x2",
      "outcome": "AWAY",
      "decimal_odds": 4.75,
      "bookmaker": "1xbet",
      "bookmakers_count": 7
    },
    "207466|over_under_15|OVER": {
      "event_id": 207466,
      "market": "over_under_15",
      "outcome": "OVER",
      "decimal_odds": 1.37,
      "bookmaker": "consensus",
      "bookmakers_count": 1
    },
    "207466|over_under_15|UNDER": {
      "event_id": 207466,
      "market": "over_under_15",
      "outcome": "UNDER",
      "decimal_odds": 2.9,
      "bookmaker": "betway",
      "bookmakers_count": 1
    },
    "207466|over_under_25|OVER": {
      "event_id": 207466,
      "market": "over_under_25",
      "outcome": "OVER",
      "decimal_odds": 2.255,
      "bookmaker": "1xbet",
      "bookmakers_count": 1
    },
    "207466|over_under_25|UNDER": {
      "event_id": 207466,
      "market": "over_under_25",
      "outcome": "UNDER",
      "decimal_odds": 1.733,
      "bookmaker": "1xbet",
      "bookmakers_count": 1
    },
    "207466|over_under_35|OVER": {
      "event_id": 207466,
      "market": "over_under_35",
      "outcome": "OVER",
      "decimal_odds": 4.0,
      "bookmaker": "consensus",
      "bookmakers_count": 1
    },
    "207466|over_under_35|UNDER": {
      "event_id": 207466,
      "market": "over_under_35",
      "outcome": "UNDER",
      "decimal_odds": 1.222,
      "bookmaker": "betway",
      "bookmakers_count": 1
    },
    "207466|btts|YES": {
      "event_id": 207466,
      "market": "btts",
      "outcome": "YES",
      "decimal_odds": 2.02,
      "bookmaker": "consensus",
      "bookmakers_count": 7
    },
    "207466|btts|NO": {
      "event_id": 207466,
      "market": "btts",
      "outcome": "NO",
      "decimal_odds": 1.74,
      "bookmaker": "1xbet",
      "bookmakers_count": 7
    },
    "206684|1x2|HOME": {
      "event_id": 206684,
      "market": "1x2",
      "outcome": "HOME",
      "decimal_odds": 1.35,
      "bookmaker": "consensus",
      "bookmakers_count": 16
    },
    "206684|1x2|DRAW": {
      "event_id": 206684,
      "market": "1x2",
      "outcome": "DRAW",
      "decimal_odds": 5.76,
      "bookmaker": "1xbet",
      "bookmakers_count": 16
    },
    "206684|1x2|AWAY": {
      "event_id": 206684,
      "market": "1x2",
      "outcome": "AWAY",
      "decimal_odds": 10.5,
      "bookmaker": "1xbet",
      "bookmakers_count": 16
    },
    "206684|over_under_15|OVER": {
      "event_id": 206684,
      "market": "over_under_15",
      "outcome": "OVER",
      "decimal_odds": 1.19,
      "bookmaker": "betano",
      "bookmakers_count": 1
    },
    "206684|over_under_15|UNDER": {
      "event_id": 206684,
      "market": "over_under_15",
      "outcome": "UNDER",
      "decimal_odds": 5.0,
      "bookmaker": "bet365",
      "bookmakers_count": 1
    },
    "206684|over_under_25|OVER": {
      "event_id": 206684,
      "market": "over_under_25",
      "outcome": "OVER",
      "decimal_odds": 1.644,
      "bookmaker": "1xbet",
      "bookmakers_count": 1
    },
    "206684|over_under_25|UNDER": {
      "event_id": 206684,
      "market": "over_under_25",
      "outcome": "UNDER",
      "decimal_odds": 2.425,
      "bookmaker": "1xbet",
      "bookmakers_count": 1
    },
    "206684|over_under_35|OVER": {
      "event_id": 206684,
      "market": "over_under_35",
      "outcome": "OVER",
      "decimal_odds": 2.45,
      "bookmaker": "unibet",
      "bookmakers_count": 1
    },
    "206684|over_under_35|UNDER": {
      "event_id": 206684,
      "market": "over_under_35",
      "outcome": "UNDER",
      "decimal_odds": 1.55,
      "bookmaker": "betano",
      "bookmakers_count": 1
    },
    "206684|btts|YES": {
      "event_id": 206684,
      "market": "btts",
      "outcome": "YES",
      "decimal_odds": 1.909,
      "bookmaker": "betway",
      "bookmakers_count": 16
    },
    "206684|btts|NO": {
      "event_id": 206684,
      "market": "btts",
      "outcome": "NO",
      "decimal_odds": 1.91,
      "bookmaker": "william-hill",
      "bookmakers_count": 16
    },
    "10281|1x2|HOME": {
      "event_id": 10281,
      "market": "1x2",
      "outcome": "HOME",
      "decimal_odds": 1.25,
      "bookmaker": "novibet",
      "bookmakers_count": 16
    },
    "10281|1x2|DRAW": {
      "event_id": 10281,
      "market": "1x2",
      "outcome": "DRAW",
      "decimal_odds": 7.49,
      "bookmaker": "1xbet",
      "bookmakers_count": 16
    },
    "10281|1x2|AWAY": {
      "event_id": 10281,
      "market": "1x2",
      "outcome": "AWAY",
      "decimal_odds": 14.8,
      "bookmaker": "1xbet",
      "bookmakers_count": 16
    },
    "10281|over_under_15|OVER": {
      "event_id": 10281,
      "market": "over_under_15",
      "outcome": "OVER",
      "decimal_odds": 1.15,
      "bookmaker": "betano",
      "bookmakers_count": 1
    },
    "10281|over_under_15|UNDER": {
      "event_id": 10281,
      "market": "over_under_15",
      "outcome": "UNDER",
      "decimal_odds": 6.0,
      "bookmaker": "bet365",
      "bookmakers_count": 1
    },
    "10281|over_under_25|OVER": {
      "event_id": 10281,
      "market": "over_under_25",
      "outcome": "OVER",
      "decimal_odds": 1.475,
      "bookmaker": "bet365",
      "bookmakers_count": 1
    },
    "10281|over_under_25|UNDER": {
      "event_id": 10281,
      "market": "over_under_25",
      "outcome": "UNDER",
      "decimal_odds": 2.68,
      "bookmaker": "betsson",
      "bookmakers_count": 1
    },
    "10281|over_under_35|OVER": {
      "event_id": 10281,
      "market": "over_under_35",
      "outcome": "OVER",
      "decimal_odds": 2.256,
      "bookmaker": "1xbet",
      "bookmakers_count": 1
    },
    "10281|over_under_35|UNDER": {
      "event_id": 10281,
      "market": "over_under_35",
      "outcome": "UNDER",
      "decimal_odds": 1.732,
      "bookmaker": "1xbet",
      "bookmakers_count": 1
    },
    "10281|btts|YES": {
      "event_id": 10281,
      "market": "btts",
      "outcome": "YES",
      "decimal_odds": 2.0,
      "bookmaker": "bet365",
      "bookmakers_count": 15
    },
    "10281|btts|NO": {
      "event_id": 10281,
      "market": "btts",
      "outcome": "NO",
      "decimal_odds": 1.82,
      "bookmaker": "betsson",
      "bookmakers_count": 15
    },
    "209438|1x2|HOME": {
      "event_id": 209438,
      "market": "1x2",
      "outcome": "HOME",
      "decimal_odds": 8.7,
      "bookmaker": "1xbet",
      "bookmakers_count": 7
    },
    "209438|1x2|DRAW": {
      "event_id": 209438,
      "market": "1x2",
      "outcome": "DRAW",
      "decimal_odds": 5.44,
      "bookmaker": "1xbet",
      "bookmakers_count": 7
    },
    "209438|1x2|AWAY": {
      "event_id": 209438,
      "market": "1x2",
      "outcome": "AWAY",
      "decimal_odds": 1.385,
      "bookmaker": "1xbet",
      "bookmakers_count": 7
    },
    "209438|over_under_15|OVER": {
      "event_id": 209438,
      "market": "over_under_15",
      "outcome": "OVER",
      "decimal_odds": 1.2,
      "bookmaker": "novibet",
      "bookmakers_count": 1
    },
    "209438|over_under_15|UNDER": {
      "event_id": 209438,
      "market": "over_under_15",
      "outcome": "UNDER",
      "decimal_odds": 4.2,
      "bookmaker": "betway",
      "bookmakers_count": 1
    },
    "209438|over_under_25|OVER": {
      "event_id": 209438,
      "market": "over_under_25",
      "outcome": "OVER",
      "decimal_odds": 1.725,
      "bookmaker": "1xbet",
      "bookmakers_count": 1
    },
    "209438|over_under_25|UNDER": {
      "event_id": 209438,
      "market": "over_under_25",
      "outcome": "UNDER",
      "decimal_odds": 2.269,
      "bookmaker": "1xbet",
      "bookmakers_count": 1
    },
    "209438|over_under_35|OVER": {
      "event_id": 209438,
      "market": "over_under_35",
      "outcome": "OVER",
      "decimal_odds": 2.6,
      "bookmaker": "novibet",
      "bookmakers_count": 1
    },
    "209438|over_under_35|UNDER": {
      "event_id": 209438,
      "market": "over_under_35",
      "outcome": "UNDER",
      "decimal_odds": 1.45,
      "bookmaker": "novibet",
      "bookmakers_count": 1
    },
    "209438|btts|YES": {
      "event_id": 209438,
      "market": "btts",
      "outcome": "YES",
      "decimal_odds": 1.95,
      "bookmaker": "unibet",
      "bookmakers_count": 7
    },
    "209438|btts|NO": {
      "event_id": 209438,
      "market": "btts",
      "outcome": "NO",
      "decimal_odds": 1.86,
      "bookmaker": "consensus",
      "bookmakers_count": 7
    },
    "9096|1x2|HOME": {
      "event_id": 9096,
      "market": "1x2",
      "outcome": "HOME",
      "decimal_odds": 5.2,
      "bookmaker": "betano",
      "bookmakers_count": 16
    },
    "9096|1x2|DRAW": {
      "event_id": 9096,
      "market": "1x2",
      "outcome": "DRAW",
      "decimal_odds": 4.405,
      "bookmaker": "1xbet",
      "bookmakers_count": 16
    },
    "9096|1x2|AWAY": {
      "event_id": 9096,
      "market": "1x2",
      "outcome": "AWAY",
      "decimal_odds": 1.7,
      "bookmaker": "consensus",
      "bookmakers_count": 16
    },
    "9096|over_under_15|OVER": {
      "event_id": 9096,
      "market": "over_under_15",
      "outcome": "OVER",
      "decimal_odds": 1.16,
      "bookmaker": "betano",
      "bookmakers_count": 1
    },
    "9096|over_under_15|UNDER": {
      "event_id": 9096,
      "market": "over_under_15",
      "outcome": "UNDER",
      "decimal_odds": 5.5,
      "bookmaker": "bet365",
      "bookmakers_count": 1
    },
    "9096|over_under_25|OVER": {
      "event_id": 9096,
      "market": "over_under_25",
      "outcome": "OVER",
      "decimal_odds": 1.5,
      "bookmaker": "betano",
      "bookmakers_count": 1
    },
    "9096|over_under_25|UNDER": {
      "event_id": 9096,
      "market": "over_under_25",
      "outcome": "UNDER",
      "decimal_odds": 2.62,
      "bookmaker": "betsson",
      "bookmakers_count": 1
    },
    "9096|over_under_35|OVER": {
      "event_id": 9096,
      "market": "over_under_35",
      "outcome": "OVER",
      "decimal_odds": 2.267,
      "bookmaker": "1xbet",
      "bookmakers_count": 1
    },
    "9096|over_under_35|UNDER": {
      "event_id": 9096,
      "market": "over_under_35",
      "outcome": "UNDER",
      "decimal_odds": 1.726,
      "bookmaker": "1xbet",
      "bookmakers_count": 1
    },
    "9096|btts|YES": {
      "event_id": 9096,
      "market": "btts",
      "outcome": "YES",
      "decimal_odds": 1.55,
      "bookmaker": "betano",
      "bookmakers_count": 15
    },
    "9096|btts|NO": {
      "event_id": 9096,
      "market": "btts",
      "outcome": "NO",
      "decimal_odds": 2.48,
      "bookmaker": "betsson",
      "bookmakers_count": 15
    },
    "207922|1x2|HOME": {
      "event_id": 207922,
      "market": "1x2",
      "outcome": "HOME",
      "decimal_odds": 3.15,
      "bookmaker": "pinnacle",
      "bookmakers_count": 15
    },
    "207922|1x2|DRAW": {
      "event_id": 207922,
      "market": "1x2",
      "outcome": "DRAW",
      "decimal_odds": 3.08,
      "bookmaker": "1xbet",
      "bookmakers_count": 15
    },
    "207922|1x2|AWAY": {
      "event_id": 207922,
      "market": "1x2",
      "outcome": "AWAY",
      "decimal_odds": 2.48,
      "bookmaker": "pinnacle",
      "bookmakers_count": 15
    },
    "207922|over_under_15|OVER": {
      "event_id": 207922,
      "market": "over_under_15",
      "outcome": "OVER",
      "decimal_odds": 1.478,
      "bookmaker": "pinnacle",
      "bookmakers_count": 1
    },
    "207922|over_under_15|UNDER": {
      "event_id": 207922,
      "market": "over_under_15",
      "outcome": "UNDER",
      "decimal_odds": 2.68,
      "bookmaker": "pinnacle",
      "bookmakers_count": 1
    },
    "207922|over_under_25|OVER": {
      "event_id": 207922,
      "market": "over_under_25",
      "outcome": "OVER",
      "decimal_odds": 2.53,
      "bookmaker": "pinnacle",
      "bookmakers_count": 1
    },
    "207922|over_under_25|UNDER": {
      "event_id": 207922,
      "market": "over_under_25",
      "outcome": "UNDER",
      "decimal_odds": 1.54,
      "bookmaker": "novibet",
      "bookmakers_count": 1
    },
    "207922|over_under_35|OVER": {
      "event_id": 207922,
      "market": "over_under_35",
      "outcome": "OVER",
      "decimal_odds": 5.0,
      "bookmaker": "bet365",
      "bookmakers_count": 1
    },
    "207922|over_under_35|UNDER": {
      "event_id": 207922,
      "market": "over_under_35",
      "outcome": "UNDER",
      "decimal_odds": 1.19,
      "bookmaker": "betano",
      "bookmakers_count": 1
    },
    "207922|btts|YES": {
      "event_id": 207922,
      "market": "btts",
      "outcome": "YES",
      "decimal_odds": 2.05,
      "bookmaker": "betway",
      "bookmakers_count": 14
    },
    "207922|btts|NO": {
      "event_id": 207922,
      "market": "btts",
      "outcome": "NO",
      "decimal_odds": 1.76,
      "bookmaker": "novibet",
      "bookmakers_count": 14
    },
    "207923|1x2|HOME": {
      "event_id": 207923,
      "market": "1x2",
      "outcome": "HOME",
      "decimal_odds": 1.98,
      "bookmaker": "novibet",
      "bookmakers_count": 15
    },
    "207923|1x2|DRAW": {
      "event_id": 207923,
      "market": "1x2",
      "outcome": "DRAW",
      "decimal_odds": 3.38,
      "bookmaker": "1xbet",
      "bookmakers_count": 15
    },
    "207923|1x2|AWAY": {
      "event_id": 207923,
      "market": "1x2",
      "outcome": "AWAY",
      "decimal_odds": 4.08,
      "bookmaker": "pinnacle",
      "bookmakers_count": 15
    },
    "207923|over_under_15|OVER": {
      "event_id": 207923,
      "market": "over_under_15",
      "outcome": "OVER",
      "decimal_odds": 1.4,
      "bookmaker": "betano",
      "bookmakers_count": 1
    },
    "207923|over_under_15|UNDER": {
      "event_id": 207923,
      "market": "over_under_15",
      "outcome": "UNDER",
      "decimal_odds": 3.0,
      "bookmaker": "pinnacle",
      "bookmakers_count": 1
    },
    "207923|over_under_25|OVER": {
      "event_id": 207923,
      "market": "over_under_25",
      "outcome": "OVER",
      "decimal_odds": 2.23,
      "bookmaker": "pinnacle",
      "bookmakers_count": 1
    },
    "207923|over_under_25|UNDER": {
      "event_id": 207923,
      "market": "over_under_25",
      "outcome": "UNDER",
      "decimal_odds": 1.671,
      "bookmaker": "pinnacle",
      "bookmakers_count": 1
    },
    "207923|over_under_35|OVER": {
      "event_id": 207923,
      "market": "over_under_35",
      "outcome": "OVER",
      "decimal_odds": 4.05,
      "bookmaker": "pinnacle",
      "bookmakers_count": 1
    },
    "207923|over_under_35|UNDER": {
      "event_id": 207923,
      "market": "over_under_35",
      "outcome": "UNDER",
      "decimal_odds": 1.24,
      "bookmaker": "betano",
      "bookmakers_count": 1
    },
    "207923|btts|YES": {
      "event_id": 207923,
      "market": "btts",
      "outcome": "YES",
      "decimal_odds": 2.0,
      "bookmaker": "bet365",
      "bookmakers_count": 14
    },
    "207923|btts|NO": {
      "event_id": 207923,
      "market": "btts",
      "outcome": "NO",
      "decimal_odds": 1.8,
      "bookmaker": "interwetten",
      "bookmakers_count": 14
    },
    "8300|1x2|HOME": {
      "event_id": 8300,
      "market": "1x2",
      "outcome": "HOME",
      "decimal_odds": 1.7,
      "bookmaker": "1xbet",
      "bookmakers_count": 15
    },
    "8300|1x2|DRAW": {
      "event_id": 8300,
      "market": "1x2",
      "outcome": "DRAW",
      "decimal_odds": 4.09,
      "bookmaker": "pinnacle",
      "bookmakers_count": 15
    },
    "8300|1x2|AWAY": {
      "event_id": 8300,
      "market": "1x2",
      "outcome": "AWAY",
      "decimal_odds": 5.35,
      "bookmaker": "betsson",
      "bookmakers_count": 15
    },
    "8300|btts|YES": {
      "event_id": 8300,
      "market": "btts",
      "outcome": "YES",
      "decimal_odds": 1.862,
      "bookmaker": "pinnacle",
      "bookmakers_count": 15
    },
    "8300|btts|NO": {
      "event_id": 8300,
      "market": "btts",
      "outcome": "NO",
      "decimal_odds": 2.0,
      "bookmaker": "pinnacle",
      "bookmakers_count": 15
    },
    "8336|1x2|HOME": {
      "event_id": 8336,
      "market": "1x2",
      "outcome": "HOME",
      "decimal_odds": 1.635,
      "bookmaker": "1xbet",
      "bookmakers_count": 12
    },
    "8336|1x2|DRAW": {
      "event_id": 8336,
      "market": "1x2",
      "outcome": "DRAW",
      "decimal_odds": 4.05,
      "bookmaker": "1xbet",
      "bookmakers_count": 12
    },
    "8336|1x2|AWAY": {
      "event_id": 8336,
      "market": "1x2",
      "outcome": "AWAY",
      "decimal_odds": 6.2,
      "bookmaker": "betsson",
      "bookmakers_count": 12
    },
    "8336|btts|YES": {
      "event_id": 8336,
      "market": "btts",
      "outcome": "YES",
      "decimal_odds": 2.05,
      "bookmaker": "bet365",
      "bookmakers_count": 11
    },
    "8336|btts|NO": {
      "event_id": 8336,
      "market": "btts",
      "outcome": "NO",
      "decimal_odds": 1.8,
      "bookmaker": "william-hill",
      "bookmakers_count": 11
    }
  },
  "_pipeline_version": "v22-league-strength-engine"
}