{
  "updated_at": "2026-06-04T21:16:29.814796+00:00",
  "source": "production_qa_v1",
  "status": "production_ready",
  "score": 92,
  "summary": {
    "files_checked": 24,
    "workflows_checked": 2,
    "critical_errors": 0,
    "errors": 0,
    "warnings": 2,
    "ok": 24
  },
  "files": [
    {
      "file": "predictions.json",
      "exists": true,
      "critical": true,
      "status": "ok",
      "count": 607,
      "updated_at": "2026-06-04T21:16:29.036363+00:00",
      "age_minutes": 0.0,
      "size_bytes": 6940042,
      "notes": [],
      "source": null
    },
    {
      "file": "best_odds.json",
      "exists": true,
      "critical": true,
      "status": "ok",
      "count": 392,
      "updated_at": "2026-06-04T21:02:33.543474+00:00",
      "age_minutes": 13.9,
      "size_bytes": 540208,
      "notes": [],
      "source": "bsd_v2_odds_best"
    },
    {
      "file": "signals.json",
      "exists": true,
      "critical": true,
      "status": "ok",
      "count": 45,
      "updated_at": "2026-06-04T21:16:29.482942+00:00",
      "age_minutes": 0.0,
      "size_bytes": 384161,
      "notes": [],
      "source": null
    },
    {
      "file": "value_bets.json",
      "exists": true,
      "critical": false,
      "status": "ok",
      "count": 11,
      "updated_at": "2026-06-04T21:16:29.567027+00:00",
      "age_minutes": 0.0,
      "size_bytes": 42798,
      "notes": [],
      "source": "local_disciplined"
    },
    {
      "file": "matches_today.json",
      "exists": true,
      "critical": false,
      "status": "ok",
      "count": 25,
      "updated_at": "2026-06-04T21:02:36.664692+00:00",
      "age_minutes": 13.9,
      "size_bytes": 34780,
      "notes": [],
      "source": null
    },
    {
      "file": "standings.json",
      "exists": true,
      "critical": false,
      "status": "ok",
      "count": 48,
      "updated_at": "2026-06-04T21:03:13.390993+00:00",
      "age_minutes": 13.3,
      "size_bytes": 506285,
      "notes": [],
      "source": "season_aware"
    },
    {
      "file": "match_context.json",
      "exists": true,
      "critical": false,
      "status": "ok",
      "count": 24,
      "updated_at": "2026-06-04T21:05:59.032341+00:00",
      "age_minutes": 10.5,
      "size_bytes": 524449,
      "notes": [],
      "source": "bsd_v2_context"
    },
    {
      "file": "selection_journal.json",
      "exists": true,
      "critical": false,
      "status": "ok",
      "count": 696,
      "updated_at": "2026-06-04T21:16:29.592500+00:00",
      "age_minutes": 0.0,
      "size_bytes": 752134,
      "notes": [],
      "source": "selection_journal_v2_settlement"
    },
    {
      "file": "recent_results.json",
      "exists": true,
      "critical": false,
      "status": "ok",
      "count": 404,
      "updated_at": "2026-06-04T21:06:06.499221+00:00",
      "age_minutes": 10.4,
      "size_bytes": 823774,
      "notes": [],
      "source": "bsd_v2_events_history"
    },
    {
      "file": "performance_summary.json",
      "exists": true,
      "critical": false,
      "status": "ok",
      "count": 618,
      "updated_at": "2026-06-04T21:16:29.704366+00:00",
      "age_minutes": 0.0,
      "size_bytes": 7105,
      "notes": [],
      "source": "local_backtesting_lite"
    },
    {
      "file": "api_coverage_report.json",
      "exists": true,
      "critical": false,
      "status": "ok",
      "count": 29,
      "updated_at": "2026-06-04T21:06:26.441517+00:00",
      "age_minutes": 10.1,
      "size_bytes": 19186,
      "notes": [],
      "source": "api_coverage_scanner_v1"
    },
    {
      "file": "team_intelligence.json",
      "exists": true,
      "critical": false,
      "status": "ok",
      "count": 42,
      "updated_at": "2026-06-04T21:07:47.302062+00:00",
      "age_minutes": 8.7,
      "size_bytes": 178418,
      "notes": [],
      "source": "team_intelligence_v1"
    },
    {
      "file": "context_intelligence.json",
      "exists": true,
      "critical": false,
      "status": "ok",
      "count": 24,
      "updated_at": "2026-06-04T21:08:25.021122+00:00",
      "age_minutes": 8.1,
      "size_bytes": 75770,
      "notes": [],
      "source": "context_intelligence_v1"
    },
    {
      "file": "team_form.json",
      "exists": true,
      "critical": false,
      "status": "ok",
      "count": 43,
      "updated_at": "2026-06-04T21:08:52.431042+00:00",
      "age_minutes": 7.6,
      "size_bytes": 93293,
      "notes": [],
      "source": "team_form_v1"
    },
    {
      "file": "h2h_context.json",
      "exists": true,
      "critical": false,
      "status": "ok",
      "count": 24,
      "updated_at": "2026-06-04T21:08:52.434277+00:00",
      "age_minutes": 7.6,
      "size_bytes": 13985,
      "notes": [],
      "source": "h2h_context_v1"
    },
    {
      "file": "xg_context.json",
      "exists": true,
      "critical": false,
      "status": "ok",
      "count": 24,
      "updated_at": "2026-06-04T21:08:52.434954+00:00",
      "age_minutes": 7.6,
      "size_bytes": 13601,
      "notes": [],
      "source": "xg_context_v1"
    },
    {
      "file": "market_intelligence.json",
      "exists": true,
      "critical": false,
      "status": "ok",
      "count": 32,
      "updated_at": "2026-06-04T21:10:02.385478+00:00",
      "age_minutes": 6.5,
      "size_bytes": 1223281,
      "notes": [],
      "source": "market_intelligence_v1"
    },
    {
      "file": "compare_odds_cache.json",
      "exists": true,
      "critical": false,
      "status": "ok",
      "count": 32,
      "updated_at": "2026-06-04T21:10:02.347830+00:00",
      "age_minutes": 6.5,
      "size_bytes": 1104038,
      "notes": [],
      "source": "compare_odds_cache_v1"
    },
    {
      "file": "odds_movement.json",
      "exists": true,
      "critical": false,
      "status": "ok",
      "count": 180,
      "updated_at": "2026-06-04T21:09:34.929712+00:00",
      "age_minutes": 6.9,
      "size_bytes": 46301,
      "notes": [],
      "source": "odds_movement_v1"
    },
    {
      "file": "polymarket_context.json",
      "exists": true,
      "critical": false,
      "status": "warn",
      "count": 1,
      "updated_at": "2026-06-01T18:49:57.631647+00:00",
      "age_minutes": 4466.5,
      "size_bytes": 2271,
      "notes": [
        "stale_over_1440m"
      ],
      "source": "polymarket_context_v1"
    },
    {
      "file": "broadcasts.json",
      "exists": true,
      "critical": false,
      "status": "ok",
      "count": 600,
      "updated_at": "2026-06-04T21:08:56.134415+00:00",
      "age_minutes": 7.6,
      "size_bytes": 457177,
      "notes": [],
      "source": "broadcasts_v1"
    },
    {
      "file": "bsd_event_predictions.json",
      "exists": true,
      "critical": false,
      "status": "ok",
      "count": 10,
      "updated_at": "2026-06-04T21:09:03.092787+00:00",
      "age_minutes": 7.4,
      "size_bytes": 4763,
      "notes": [],
      "source": "bsd_event_predictions_v1"
    },
    {
      "file": "live.json",
      "exists": true,
      "critical": false,
      "status": "ok",
      "count": 3,
      "updated_at": "2026-06-04T20:21:06.594803+00:00",
      "age_minutes": 55.4,
      "size_bytes": 5276,
      "notes": [],
      "source": "bsd_v2_events_live+backfill"
    },
    {
      "file": "live_intelligence.json",
      "exists": true,
      "critical": false,
      "status": "ok",
      "count": 3,
      "updated_at": "2026-06-04T20:21:07.455514+00:00",
      "age_minutes": 55.4,
      "size_bytes": 42628,
      "notes": [],
      "source": "live_intelligence_v23"
    }
  ],
  "workflows": [
    {
      "file": ".github/workflows/fetch_daily.yml",
      "exists": true,
      "status": "warn",
      "notes": [
        "missing_token:git add data/ -f"
      ]
    },
    {
      "file": ".github/workflows/fetch_live.yml",
      "exists": true,
      "status": "ok",
      "notes": []
    }
  ],
  "recommendations": [
    "Rulează Fetch Daily Data după modificări de pipeline.",
    "Rulează Fetch Live Scores după modificări de live center.",
    "Dacă un fișier critic are count 0, verifică data/debug/*.json înainte de UI.",
    "Value Bets oficial rămâne blocat până există endpoint BSD confirmat; se folosește fallback local disciplinat."
  ],
  "_pipeline_version": "v22-full-bsd-coverage",
  "count": 0
}