{
  "updated_at": "2026-07-18T20:22:58.482351+00:00",
  "limit": 18,
  "params": {},
  "summary": {
    "live_events": 2,
    "enriched_events": 2,
    "with_stats": 2,
    "with_incidents": 2,
    "with_lineups": 2,
    "strong_signals": 0,
    "reused_cache": 0,
    "refetched": 2
  },
  "events": [
    {
      "event_id": 216373,
      "score": "0-0",
      "minute": 6,
      "last_updated": null,
      "cache_status": "refetched",
      "pressure_side": "balanced",
      "pressure_score": -7.0,
      "resources": {
        "stats": 1,
        "incidents": 1,
        "lineups": 1
      },
      "signals": [
        {
          "type": "lineups",
          "level": "info",
          "label": "lineup confirmed",
          "note": "Status lineup disponibil pentru context live."
        }
      ]
    },
    {
      "event_id": 214531,
      "score": "4-0",
      "minute": 0,
      "last_updated": "2026-07-18T20:12:36Z",
      "cache_status": "refetched",
      "pressure_side": "home",
      "pressure_score": 14.0,
      "resources": {
        "stats": 1,
        "incidents": 22,
        "lineups": 1
      },
      "signals": [
        {
          "type": "cards",
          "level": "watch",
          "label": "meci tensionat",
          "note": "4 cartonașe detectate în timeline."
        },
        {
          "type": "lineups",
          "level": "info",
          "label": "lineup confirmed",
          "note": "Status lineup disponibil pentru context live."
        }
      ]
    }
  ],
  "requests": [
    {
      "label": "events_live",
      "url": "https://sports.bzzoiro.com/api/v2/events/live/",
      "params": {},
      "status": 200,
      "elapsed_ms": 289
    },
    {
      "label": "backfill_event_216373",
      "url": "https://sports.bzzoiro.com/api/v2/events/216373/",
      "params": {},
      "status": 200,
      "elapsed_ms": 709
    },
    {
      "label": "live_lineups_214531",
      "url": "https://sports.bzzoiro.com/api/v2/events/214531/lineups/",
      "params": {},
      "status": 200,
      "elapsed_ms": 297
    },
    {
      "label": "live_incidents_214531",
      "url": "https://sports.bzzoiro.com/api/v2/events/214531/incidents/",
      "params": {},
      "status": 200,
      "elapsed_ms": 305
    },
    {
      "label": "live_stats_216373",
      "url": "https://sports.bzzoiro.com/api/v2/events/216373/stats/",
      "params": {},
      "status": 200,
      "elapsed_ms": 304
    },
    {
      "label": "live_incidents_216373",
      "url": "https://sports.bzzoiro.com/api/v2/events/216373/incidents/",
      "params": {},
      "status": 200,
      "elapsed_ms": 304
    },
    {
      "label": "live_lineups_216373",
      "url": "https://sports.bzzoiro.com/api/v2/events/216373/lineups/",
      "params": {},
      "status": 200,
      "elapsed_ms": 486
    },
    {
      "label": "live_stats_214531",
      "url": "https://sports.bzzoiro.com/api/v2/events/214531/stats/",
      "params": {},
      "status": 200,
      "elapsed_ms": 717
    }
  ],
  "warnings": []
}