{
  "generated_at": "2026-06-09T16:13:26+00:00",
  "summary": {
    "total_scanned": 29,
    "safe_count": 0,
    "watchlist_count": 10,
    "rejected_count": 19,
    "top_rejection_reasons": [
      [
        "GRADE_BELOW_A",
        29
      ],
      [
        "NOT_TODAY_MATCH",
        25
      ],
      [
        "STRATEGY_NOT_IN_SAFE_ALLOWLIST",
        15
      ],
      [
        "DOWNGRADED",
        14
      ],
      [
        "EV_NEGATIVE_OR_ZERO",
        14
      ],
      [
        "WEAK_LEAGUE",
        13
      ],
      [
        "STRATEGY_ROI_NEGATIVE",
        12
      ],
      [
        "MARKET_NOT_IN_SAFE_ALLOWLIST",
        1
      ]
    ]
  },
  "published_summary": {
    "published_count": 0,
    "max_published_per_day": 5
  },
  "journal_summary": {
    "count": 2,
    "pending": 2,
    "settled": 0
  }
}