{
  "started_at": "2026-06-27T18:28:02.591518+00:00",
  "ended_at": "2026-06-27T18:28:02.665752+00:00",
  "n_total": 758,
  "oos": {
    "n_total": 304,
    "n_v5_kept": 304,
    "n_v6_kept": 227,
    "n_skipped_by_v6": 77,
    "skipped_losses_avoided": 16,
    "skipped_wins_lost": 61,
    "units_saved_from_avoided_losses": 16.0,
    "units_lost_from_avoided_wins": -24.05,
    "net_units_impact": 40.05,
    "v5_roi_pct": 8.51,
    "v6_roi_pct": 7.85,
    "roi_delta_pp": -0.66,
    "v5_win_rate_pct": 69.4,
    "v6_win_rate_pct": 66.1,
    "v5_total_profit": 25.86,
    "v6_total_profit": 17.81
  },
  "in_sample": {
    "n_total": 758,
    "n_v5_kept": 758,
    "n_v6_kept": 410,
    "n_skipped_by_v6": 348,
    "skipped_losses_avoided": 127,
    "skipped_wins_lost": 221,
    "units_saved_from_avoided_losses": 127.0,
    "units_lost_from_avoided_wins": -89.67,
    "net_units_impact": 216.67,
    "v5_roi_pct": 2.9,
    "v6_roi_pct": 14.46,
    "roi_delta_pp": 11.56,
    "v5_win_rate_pct": 68.3,
    "v6_win_rate_pct": 72.4,
    "v5_total_profit": 21.96,
    "v6_total_profit": 59.29
  }
}